{
  "$schema": "https://developer.microsoft.com/json-schemas/fabric/item/report/definition/visualContainer/2.4.0/schema.json",
  "name": "matrix04_monthly",
  "position": {
    "x": 328.75,
    "y": 417.5,
    "z": 4000,
    "height": 263.75,
    "width": 748.75,
    "tabOrder": 5000
  },
  "visual": {
    "visualType": "pivotTable",
    "query": {
      "queryState": {
        "Columns": {
          "projections": [
            {
              "field": {
                "Column": {
                  "Expression": {
                    "SourceRef": {
                      "Entity": "Dim Area"
                    }
                  },
                  "Property": "omraade_navn"
                }
              },
              "queryRef": "Dim Area.omraade_navn",
              "active": true
            }
          ]
        },
        "Rows": {
          "projections": [
            {
              "field": {
                "Column": {
                  "Expression": {
                    "SourceRef": {
                      "Entity": "KPI Measures"
                    }
                  },
                  "Property": "Month-Year"
                }
              },
              "queryRef": "KPI Measures.Month-Year",
              "active": true
            }
          ]
        },
        "Values": {
          "projections": [
            {
              "field": {
                "Measure": {
                  "Expression": {
                    "SourceRef": {
                      "Entity": "KPI Measures"
                    }
                  },
                  "Property": "Total Magasininnhold (GWh)"
                }
              },
              "queryRef": "KPI Measures.Total Magasininnhold (GWh)",
              "active": true
            }
          ]
        }
      }
    },
    "objects": {
      "values": [
        {
          "properties": {}
        }
      ],
      "total": [
        {
          "properties": {
            "fontColor": {
              "solid": {
                "color": {
                  "expr": {
                    "Literal": {
                      "Value": "'#118DFF'"
                    }
                  }
                }
              }
            },
            "fontSize": {
              "expr": {
                "Literal": {
                  "Value": "12D"
                }
              }
            },
            "fontFamily": {
              "expr": {
                "Literal": {
                  "Value": "'Segoe UI Semibold, wf_segoe-ui_semibold, helvetica, arial, sans-serif'"
                }
              }
            }
          }
        }
      ]
    }
  }
}