{
  "$schema": "https://developer.microsoft.com/json-schemas/fabric/item/report/definition/visualContainer/2.4.0/schema.json",
  "name": "3fa1c96f6b9aa957bbdd",
  "position": {
    "x": 850,
    "y": 10,
    "z": 3000,
    "height": 60,
    "width": 180,
    "tabOrder": 2000
  },
  "visual": {
    "visualType": "slicer",
    "query": {
      "queryState": {
        "Filters": {
          "projections": [
            {
              "field": {
                "Column": {
                  "Expression": {
                    "SourceRef": {
                      "Entity": "Dim Date"
                    }
                  },
                  "Property": "date"
                }
              },
              "queryRef": "Dim Date.date",
              "active": true
            }
          ]
        }
      }
    },
    "objects": {
      "data": [
        {
          "properties": {
            "mode": {
              "expr": {
                "Literal": {
                  "Value": "'between'"
                }
              }
            }
          }
        }
      ]
    }
  }
}